{
  "items": [
    {
      "description": "Инди-студия разрабатывающая настольные игры",
      "cost": 200000,
	  "assetID": 1,
      "cashFlow": -15000
    },
    {
      "description": "Квартира в доме барачного типа",
      "cost": 100000,
	  "assetID": 2,
      "cashFlow": 40000
    },
    {
      "description": "Однокомнатная квартира на окраине города",
      "cost": 5000000,
	  "assetID": 3,
      "cashFlow": 120000
    },
    {
      "description": "Загороженый участок земли площадью 3 сотки в промышленном районе",
      "cost": 1500000,
	  "assetID": 4,
      "cashFlow": 50000
    },
    {
      "description": "участок земли в центре города",
      "cost": 4500000,
	  "assetID": 5,
      "cashFlow": 150000
    }
  ]
}